envconsul/__init__.py
envconsul/consts.py
envconsul/envconsul.py
envconsul/errors.py
envconsul/utils.py
envconsul-1.0.0.dist-info/DESCRIPTION.rst
envconsul-1.0.0.dist-info/METADATA
envconsul-1.0.0.dist-info/metadata.json
envconsul-1.0.0.dist-info/RECORD
envconsul-1.0.0.dist-info/top_level.txt
envconsul-1.0.0.dist-info/WHEEL
