Metadata-Version: 2.0
Name: envconsul
Version: 1.0.0
Summary: Environment Variable and Settings Management via Consul
Home-page: https://github.com/cevaris/python-envconsul
Author: Adam Cardenas
Author-email: cevaris@gmail.com
License: MIT
Keywords: envconsul
Platform: UNKNOWN
Classifier: Development Status :: 2 - Pre-Alpha
Classifier: Intended Audience :: Developers
Classifier: License :: OSI Approved :: BSD License
Classifier: Natural Language :: English
Classifier: Programming Language :: Python :: 2.7
Requires-Dist: consulate (==0.2.0)
Requires-Dist: tornado (==4.1)
